[
  {
    "timestamp": "2025-08-07T19:04:42.274932",
    "type": "singles_series",
    "players": [
      "Noah",
      "Jack_L"
    ],
    "sets": [
      {
        "games": [
          6,
          2
        ],
        "kind": "set"
      },
      {
        "games": [
          6,
          4
        ],
        "kind": "set"
      }
    ],
    "winner": "A"
  },
  {
    "timestamp": "2025-08-07T19:13:07.484426",
    "type": "doubles_series",
    "teams": [
      [
        "Spencer",
        "Aliza"
      ],
      [
        "Emma",
        "Anderson"
      ]
    ],
    "sets": [
      {
        "games": [
          1,
          6
        ],
        "kind": "set"
      },
      {
        "games": [
          6,
          2
        ],
        "kind": "set"
      },
      {
        "games": [
          6,
          10
        ],
        "kind": "tiebreak"
      }
    ],
    "winner": "B"
  },
  {
    "timestamp": "2025-08-07T19:16:09.897952",
    "type": "doubles_series",
    "teams": [
      [
        "Jill",
        "Rhys"
      ],
      [
        "Liam",
        "Jack_L"
      ]
    ],
    "sets": [
      {
        "games": [
          1,
          6
        ],
        "kind": "set"
      },
      {
        "games": [
          6,
          3
        ],
        "kind": "set"
      },
      {
        "games": [
          10,
          5
        ],
        "kind": "tiebreak"
      }
    ],
    "winner": "A"
  },
  {
    "timestamp": "2025-08-07T19:17:18.069424",
    "type": "singles_series",
    "players": [
      "Jack_W",
      "Aaron"
    ],
    "sets": [
      {
        "games": [
          3,
          6
        ],
        "kind": "set"
      },
      {
        "games": [
          0,
          6
        ],
        "kind": "set"
      }
    ],
    "winner": "B"
  },
  {
    "timestamp": "2025-08-07T19:18:04.174247",
    "type": "singles_series",
    "players": [
      "Ishan",
      "Rishaan"
    ],
    "sets": [
      {
        "games": [
          4,
          6
        ],
        "kind": "set"
      },
      {
        "games": [
          6,
          2
        ],
        "kind": "set"
      },
      {
        "games": [
          5,
          7
        ],
        "kind": "tiebreak"
      }
    ],
    "winner": "B"
  },
  {
    "timestamp": "2025-08-07T19:18:44.593633",
    "type": "singles_series",
    "players": [
      "Emma",
      "Anderson"
    ],
    "sets": [
      {
        "games": [
          6,
          2
        ],
        "kind": "set"
      }
    ],
    "winner": "A"
  },
  {
    "timestamp": "2025-08-07T19:19:29.731797",
    "type": "doubles_series",
    "teams": [
      [
        "Rishaan",
        "Ben"
      ],
      [
        "Aaron",
        "Jack_W"
      ]
    ],
    "sets": [
      {
        "games": [
          6,
          2
        ],
        "kind": "set"
      },
      {
        "games": [
          6,
          3
        ],
        "kind": "set"
      }
    ],
    "winner": "A"
  }
]